MANIFEST.in
README
README.md
setup.py
debug_print/VERSION
debug_print/__init__.py
debug_print/debug_print_impl.py
debug_print.egg-info/PKG-INFO
debug_print.egg-info/SOURCES.txt
debug_print.egg-info/dependency_links.txt
debug_print.egg-info/not-zip-safe
debug_print.egg-info/top_level.txt