Metadata-Version: 1.0
Name: debug-print
Version: 0.6.1
Summary: A mini library for printf style debugging.
Home-page: http://crouchofthewildtiger.com/
Author: Roman A. Taycher
Author-email: rtaycher1987@gmail.com
License: MIT/X11 License
Keywords: debug printf-debugging
Platform: UNKNOWN
